googleforms_etl/__init__.py
googleforms_etl/api/__init__.py
googleforms_etl/api/drive.py
googleforms_etl/api/forms.py
googleforms_etl/auth/__init__.py
googleforms_etl/auth/authenticate.py
googleforms_etl/utils/__init__.py
googleforms_etl/utils/watermark.py
googleforms_etl-0.2.1.dist-info/licenses/LICENSE
googleforms_etl-0.2.1.dist-info/METADATA
googleforms_etl-0.2.1.dist-info/WHEEL
googleforms_etl-0.2.1.dist-info/top_level.txt
googleforms_etl-0.2.1.dist-info/RECORD
