Metadata-Version: 2.4
Name: googleforms_etl
Version: 0.2.1
Summary: Databricks-first Google Forms + Drive API wrapper for data workflows (ETL, normalization, file uploads).
Author-email: Rushank Sheta <sheta.rushank@gmail.com>
License: Apache-2.0
Project-URL: Homepage, https://github.com/rushanksheta/googleforms_etl
Project-URL: Repository, https://github.com/rushanksheta/googleforms_etl
Project-URL: Issues, https://github.com/rushanksheta/googleforms_etl/issues
Requires-Python: >=3.9
License-File: LICENSE
Requires-Dist: google-api-python-client>=2.0
Requires-Dist: google-auth>=2.0
Requires-Dist: google-auth-httplib2>=0.2.0
Requires-Dist: google-auth-oauthlib>=1.0.0
Requires-Dist: beartype>=0.16
Provides-Extra: pandas
Requires-Dist: pandas>=2.0; extra == "pandas"
Provides-Extra: gcs
Requires-Dist: google-cloud-storage>=2.10; extra == "gcs"
Provides-Extra: spark
Requires-Dist: pyspark>=3.3; extra == "spark"
Provides-Extra: delta
Requires-Dist: delta-spark>=3.0; extra == "delta"
Provides-Extra: databricks
Requires-Dist: pandas>=2.0; extra == "databricks"
Requires-Dist: pyspark>=3.3; extra == "databricks"
Requires-Dist: delta-spark>=3.0; extra == "databricks"
Dynamic: license-file
